models/__init__.py
models/schemas/__init__.py
models/schemas/acme_envelope_ingest_v1.json
models/schemas/acme_envelope_rejection_v1.json
models/schemas/acme_envelope_widget_v1.json
models/schemas/acme_payload_widget_v1.json
models/tests/__init__.py
models/tests/conftest.py
models/tests/schemas_test.py
models/tests/validation_test.py
models/validation.py
acme_widgets_models-0.1.0.dist-info/METADATA
acme_widgets_models-0.1.0.dist-info/WHEEL
acme_widgets_models-0.1.0.dist-info/RECORD
