Metadata-Version: 2.1
Name: acme-widgets-models
Version: 0.1.0
Summary: contains schemas and related utility functions used within the acme widgets solution
Home-page: https://github.com/acme-widgets-org/models
License: Proprietary
Keywords: schema,validation,envelopes,payloads
Author: Craig Saxton
Author-email: csaxton171@gmail.com
Requires-Python: >=3.11,<4.0
Classifier: License :: Other/Proprietary License
Classifier: Programming Language :: Python :: 3
Classifier: Programming Language :: Python :: 3.11
Classifier: Programming Language :: Python :: 3.12
Requires-Dist: jsonschema (>=4.19.1,<5.0.0)
Project-URL: Repository, https://github.com/acme-widgets-org/models
